octicons/__init__.py
octicons/_escape_utils.py
octicons/apps.py
octicons/data.json
octicons/octicons.py
octicons/store.py
octicons/templatetags/__init__.py
octicons/templatetags/octicons.py
octicons/test/__init__.py
octicons-2.1.0.dist-info/METADATA
octicons-2.1.0.dist-info/WHEEL
octicons-2.1.0.dist-info/top_level.txt
octicons-2.1.0.dist-info/RECORD
